CStlKuaisuRumenCYuyanZhongwenwang/README.md
CStlKuaisuRumenCYuyanZhongwenwang/__init__.py
CStlKuaisuRumenCYuyanZhongwenwang/__main__.py
CStlKuaisuRumenCYuyanZhongwenwang/file.epub
CStlKuaisuRumenCYuyanZhongwenwang/index.html
CStlKuaisuRumenCYuyanZhongwenwang/css/__init__.py
CStlKuaisuRumenCYuyanZhongwenwang/css/annotations.css
CStlKuaisuRumenCYuyanZhongwenwang/css/main.css
CStlKuaisuRumenCYuyanZhongwenwang/css/normalize.css
CStlKuaisuRumenCYuyanZhongwenwang/css/popup.css
CStlKuaisuRumenCYuyanZhongwenwang/font/__init__.py
CStlKuaisuRumenCYuyanZhongwenwang/font/fontello.eot
CStlKuaisuRumenCYuyanZhongwenwang/font/fontello.svg
CStlKuaisuRumenCYuyanZhongwenwang/font/fontello.ttf
CStlKuaisuRumenCYuyanZhongwenwang/font/fontello.woff
CStlKuaisuRumenCYuyanZhongwenwang/img/__init__.py
CStlKuaisuRumenCYuyanZhongwenwang/img/annotator-glyph-sprite.png
CStlKuaisuRumenCYuyanZhongwenwang/img/annotator-icon-sprite.png
CStlKuaisuRumenCYuyanZhongwenwang/img/apple-touch-icon.png
CStlKuaisuRumenCYuyanZhongwenwang/img/cancelfullscreen.png
CStlKuaisuRumenCYuyanZhongwenwang/img/close.png
CStlKuaisuRumenCYuyanZhongwenwang/img/fullscreen.png
CStlKuaisuRumenCYuyanZhongwenwang/img/loader.gif
CStlKuaisuRumenCYuyanZhongwenwang/img/menu-icon.png
CStlKuaisuRumenCYuyanZhongwenwang/img/save.png
CStlKuaisuRumenCYuyanZhongwenwang/img/saved.png
CStlKuaisuRumenCYuyanZhongwenwang/img/settings-s.png
CStlKuaisuRumenCYuyanZhongwenwang/img/settings.png
CStlKuaisuRumenCYuyanZhongwenwang/img/star.png
CStlKuaisuRumenCYuyanZhongwenwang/js/__init__.py
CStlKuaisuRumenCYuyanZhongwenwang/js/epub.js
CStlKuaisuRumenCYuyanZhongwenwang/js/epub.min.js
CStlKuaisuRumenCYuyanZhongwenwang/js/epub.min.map
CStlKuaisuRumenCYuyanZhongwenwang/js/hooks.min.js
CStlKuaisuRumenCYuyanZhongwenwang/js/hooks.min.map
CStlKuaisuRumenCYuyanZhongwenwang/js/reader.js
CStlKuaisuRumenCYuyanZhongwenwang/js/reader.js.map
CStlKuaisuRumenCYuyanZhongwenwang/js/reader.min.js
CStlKuaisuRumenCYuyanZhongwenwang/js/reader.min.map
c_stl_kuaisu_rumen_c_yuyan_zhongwenwang-2024.3.4.0.dist-info/METADATA
c_stl_kuaisu_rumen_c_yuyan_zhongwenwang-2024.3.4.0.dist-info/WHEEL
c_stl_kuaisu_rumen_c_yuyan_zhongwenwang-2024.3.4.0.dist-info/entry_points.txt
c_stl_kuaisu_rumen_c_yuyan_zhongwenwang-2024.3.4.0.dist-info/top_level.txt
c_stl_kuaisu_rumen_c_yuyan_zhongwenwang-2024.3.4.0.dist-info/RECORD
